pqg/__init__.py
pqg/__main__.py
pqg/arguments.py
pqg/entity.py
pqg/generator.py
pqg/group_by_aggregation.py
pqg/merge.py
pqg/operation.py
pqg/projection.py
pqg/query.py
pqg/query_builder.py
pqg/query_pool.py
pqg/query_structure.py
pqg/schema.py
pqg/selection.py
pqg-0.3.2.dist-info/METADATA
pqg-0.3.2.dist-info/WHEEL
pqg-0.3.2.dist-info/entry_points.txt
pqg-0.3.2.dist-info/RECORD
