Metadata-Version: 2.3
Name: pqg
Version: 0.3.2
Summary: A synthetic pandas query generation tool
Project-URL: Homepage, https://github.com/DISLMcGill/pandas-query-generator
Project-URL: Issues, https://github.com/DISLMcGill/pandas-query-generator/issues
Requires-Python: >=3.12
Requires-Dist: pandas>=2.2.0
Requires-Dist: tqdm>=4.66.2
